hex_7seg_decoder.v
// HEXADECIMAL SEVEN SEGMENT DECODER:
module hex_7seg_decoder #(parameter COMMON_ANODE_CATHODE = 1) (in,o_a,o_b,o_c,o_d,o_e,o_f,o_g); // 0 for common anode and 1 for common cathode
input [3:0]in;
output o_a;
output o_b;
output o_c;
output o_d;
output o_e;
output o_f;
output o_g;

reg a,b,c,d,e,f,g;
always @(*) begin
    case(in) 
    4'd0 : {a,b,c,d,e,f,g} = 7'b1111110;  // common cathode value 
    4'd1 : {a,b,c,d,e,f,g} = 7'b0110000;
    4'd2 : {a,b,c,d,e,f,g} = 7'b1101101;
    4'd3 : {a,b,c,d,e,f,g} = 7'b1111001;
    4'd4 : {a,b,c,d,e,f,g} = 7'b0110011;
    4'd5 : {a,b,c,d,e,f,g} = 7'b1011011;
    4'd6 : {a,b,c,d,e,f,g} = 7'b1011111;
    4'd7 : {a,b,c,d,e,f,g} = 7'b1110000;
    4'd8 : {a,b,c,d,e,f,g} = 7'b1111111;
    4'd9 : {a,b,c,d,e,f,g} = 7'b1111011;
   4'd10 : {a,b,c,d,e,f,g} = 7'b1110111;
    4'd11: {a,b,c,d,e,f,g} = 7'b0011111;
   4'd12 : {a,b,c,d,e,f,g} = 7'b1001110;
    4'd13: {a,b,c,d,e,f,g} = 7'b0111101;
    4'd14: {a,b,c,d,e,f,g} = 7'b1001111;
    4'd15: {a,b,c,d,e,f,g} = 7'b1000111;
 default : {a,b,c,d,e,f,g} = 7'b1111110;  
    endcase
end

assign {o_a,o_b,o_c,o_d,o_e,o_f,o_g} = COMMON_ANODE_CATHODE ? {a,b,c,d,e,f,g} :~{a,b,c,d,e,f,g};

endmodule

adder_nbit.v
module adder_nbit #(parameter N=3)(a,b,sum);
input [N-1:0]a;
input [N-1:0]b;
output  reg [N:0]sum;
always @(*) begin
sum[N:0] = a[N-1:0]+b[N-1:0];  // sum = a+b
    
end
endmodule

adder_nbit_top.v
module adder_nbit_top #(parameter N = 3)(
    input [N-1:0]i_a,
    input [N-1:0]i_b, 
    output [N:0]o_sum,  //  sum in binary 
    output [6:0]O_HEX  // sum in hexadecimal 
);
// instantiation of  first module which give output in binary
adder_nbit #(.N(N)) m1(.a(i_a),.b(i_b),.sum(o_sum));

  // Internal wire for seven-seg outputs
  wire [6:0] seg_out;
// instantiation of second  module which give output in hexadecimal 
 hex_7seg_decoder #(.COMMON_ANODE_CATHODE(1)) m2(
 .in(o_sum[3:0]),
.o_a(seg_out[6]),
.o_b(seg_out[5]),
.o_c(seg_out[4]),
.o_d(seg_out[3]),
.o_e(seg_out[2]),
.o_f(seg_out[1]),
.o_g(seg_out[0])
);

// Drive top-level output
  assign O_HEX = seg_out;

endmodule

adder_nbit_top_tb.v
`timescale 1us/1ns
module stimulus;
 localparam N =3;
    reg [N-1:0]i_a;
    reg [N-1:0]i_b; 
    wire [N:0]o_sum;  //  sum in binary 
    wire [6:0]o_HEX;  // sum in hexadecimal 
// instantiation of  first module which give output in binary
adder_nbit_top  #(.N(3)) TOP(i_a,i_b,o_sum,o_HEX);

initial begin
     $dumpfile("nbit_adder_top.vcd");
      $dumpvars(0, stimulus);
$monitor($time,"i_a = %d,    i_b = %d,    o_sum = %d,  segmented_display = %b",i_a,i_b,o_sum,o_HEX);
#1; i_a = 0; i_b = 0;
for (integer i = 0 ;i<2**N;i++) begin
    for (integer j  = 0;j<2**N ;j++) begin
        #1; i_a =i; i_b = j;
    end
end
end
endmodule

// iverilog -o adder_nbit_top_tb.out adder_nbit_top.v adder_nbit.v hex_7seg_decoder.v  adder_nbit_top_tb.v
// vvp adder_nbit_top_tb.out
// dumpfile("dump.vcd");
// dumpvars(0, stimulus);
// gtkwave nbit_adder_top.vcd

nbit_adder_top.vcd
$date
	Sun Feb 22 13:04:45 2026
$end
$version
	Icarus Verilog
$end
$timescale
	1ns
$end
$scope module stimulus $end
$var wire 4 ! o_sum [3:0] $end
$var wire 7 " o_HEX [6:0] $end
$var parameter 32 # N $end
$var reg 3 $ i_a [2:0] $end
$var reg 3 % i_b [2:0] $end
$scope module TOP $end
$var wire 7 & O_HEX [6:0] $end
$var wire 3 ' i_a [2:0] $end
$var wire 3 ( i_b [2:0] $end
$var wire 7 ) seg_out [6:0] $end
$var wire 4 * o_sum [3:0] $end
$var parameter 32 + N $end
$scope module m1 $end
$var wire 3 , a [2:0] $end
$var wire 3 - b [2:0] $end
$var parameter 32 . N $end
$var reg 4 / sum [3:0] $end
$upscope $end
$scope module m2 $end
$var wire 4 0 in [3:0] $end
$var wire 1 1 o_g $end
$var wire 1 2 o_f $end
$var wire 1 3 o_e $end
$var wire 1 4 o_d $end
$var wire 1 5 o_c $end
$var wire 1 6 o_b $end
$var wire 1 7 o_a $end
$var parameter 32 8 COMMON_ANODE_CATHODE $end
$var reg 1 9 a $end
$var reg 1 : b $end
$var reg 1 ; c $end
$var reg 1 < d $end
$var reg 1 = e $end
$var reg 1 > f $end
$var reg 1 ? g $end
$upscope $end
$upscope $end
$scope begin $ivl_for_loop0 $end
$var integer 32 @ i [31:0] $end
$scope begin $ivl_for_loop1 $end
$var integer 32 A j [31:0] $end
$upscope $end
$upscope $end
$upscope $end
$enddefinitions $end
$comment Show the parameter values. $end
$dumpall
b1 8
b11 .
b11 +
b11 #
$end
#0
$dumpvars
bx A
bx @
x?
x>
x=
x<
x;
x:
x9
x7
x6
x5
x4
x3
x2
x1
bx 0
bx /
bx -
bx ,
bx *
bx )
bx (
bx '
bx &
bx %
bx $
bx "
bx !
$end
#1000
17
16
15
14
13
12
b1111110 "
b1111110 &
b1111110 )
01
19
1:
1;
1<
1=
1>
0?
b0 !
b0 *
b0 /
b0 0
b0 A
b0 @
b0 %
b0 (
b0 -
b0 $
b0 '
b0 ,
#2000
b1 A
#3000
07
04
03
b110000 "
b110000 &
b110000 )
02
09
0<
0=
0>
b1 !
b1 *
b1 /
b1 0
b10 A
b1 %
b1 (
b1 -
#4000
17
05
14
13
b1101101 "
b1101101 &
b1101101 )
11
19
0;
1<
1=
1?
b10 !
b10 *
b10 /
b10 0
b11 A
b10 %
b10 (
b10 -
#5000
15
b1111001 "
b1111001 &
b1111001 )
03
1;
0=
b11 !
b11 *
b11 /
b11 0
b100 A
b11 %
b11 (
b11 -
#6000
07
04
b110011 "
b110011 &
b110011 )
12
09
0<
1>
b100 !
b100 *
b100 /
b100 0
b101 A
b100 %
b100 (
b100 -
#7000
17
06
b1011011 "
b1011011 &
b1011011 )
14
19
0:
1<
b101 !
b101 *
b101 /
b101 0
b110 A
b101 %
b101 (
b101 -
#8000
b1011111 "
b1011111 &
b1011111 )
13
1=
b110 !
b110 *
b110 /
b110 0
b111 A
b110 %
b110 (
b110 -
#9000
16
04
03
02
b1110000 "
b1110000 &
b1110000 )
01
1:
0<
0=
0>
0?
b111 !
b111 *
b111 /
b111 0
b1 @
b0 A
b111 %
b111 (
b111 -
#10000
b110000 "
b110000 &
b110000 )
07
09
b1 !
b1 *
b1 /
b1 0
b1 A
b0 %
b0 (
b0 -
b1 $
b1 '
b1 ,
#11000
17
05
14
13
b1101101 "
b1101101 &
b1101101 )
11
19
0;
1<
1=
1?
b10 !
b10 *
b10 /
b10 0
b10 A
b1 %
b1 (
b1 -
#12000
15
b1111001 "
b1111001 &
b1111001 )
03
1;
0=
b11 !
b11 *
b11 /
b11 0
b11 A
b10 %
b10 (
b10 -
#13000
07
04
b110011 "
b110011 &
b110011 )
12
09
0<
1>
b100 !
b100 *
b100 /
b100 0
b100 A
b11 %
b11 (
b11 -
#14000
17
06
b1011011 "
b1011011 &
b1011011 )
14
19
0:
1<
b101 !
b101 *
b101 /
b101 0
b101 A
b100 %
b100 (
b100 -
#15000
b1011111 "
b1011111 &
b1011111 )
13
1=
b110 !
b110 *
b110 /
b110 0
b110 A
b101 %
b101 (
b101 -
#16000
16
04
03
02
b1110000 "
b1110000 &
b1110000 )
01
1:
0<
0=
0>
0?
b111 !
b111 *
b111 /
b111 0
b111 A
b110 %
b110 (
b110 -
#17000
14
13
12
b1111111 "
b1111111 &
b1111111 )
11
1<
1=
1>
1?
b1000 !
b1000 *
b1000 /
b1000 0
b10 @
b0 A
b111 %
b111 (
b111 -
#18000
05
b1101101 "
b1101101 &
b1101101 )
02
0;
0>
b10 !
b10 *
b10 /
b10 0
b1 A
b0 %
b0 (
b0 -
b10 $
b10 '
b10 ,
#19000
15
b1111001 "
b1111001 &
b1111001 )
03
1;
0=
b11 !
b11 *
b11 /
b11 0
b10 A
b1 %
b1 (
b1 -
#20000
07
04
b110011 "
b110011 &
b110011 )
12
09
0<
1>
b100 !
b100 *
b100 /
b100 0
b11 A
b10 %
b10 (
b10 -
#21000
17
06
b1011011 "
b1011011 &
b1011011 )
14
19
0:
1<
b101 !
b101 *
b101 /
b101 0
b100 A
b11 %
b11 (
b11 -
#22000
b1011111 "
b1011111 &
b1011111 )
13
1=
b110 !
b110 *
b110 /
b110 0
b101 A
b100 %
b100 (
b100 -
#23000
16
04
03
02
b1110000 "
b1110000 &
b1110000 )
01
1:
0<
0=
0>
0?
b111 !
b111 *
b111 /
b111 0
b110 A
b101 %
b101 (
b101 -
#24000
14
13
12
b1111111 "
b1111111 &
b1111111 )
11
1<
1=
1>
1?
b1000 !
b1000 *
b1000 /
b1000 0
b111 A
b110 %
b110 (
b110 -
#25000
b1111011 "
b1111011 &
b1111011 )
03
0=
b1001 !
b1001 *
b1001 /
b1001 0
b11 @
b0 A
b111 %
b111 (
b111 -
#26000
b1111001 "
b1111001 &
b1111001 )
02
0>
b11 !
b11 *
b11 /
b11 0
b1 A
b0 %
b0 (
b0 -
b11 $
b11 '
b11 ,
#27000
07
04
b110011 "
b110011 &
b110011 )
12
09
0<
1>
b100 !
b100 *
b100 /
b100 0
b10 A
b1 %
b1 (
b1 -
#28000
17
06
b1011011 "
b1011011 &
b1011011 )
14
19
0:
1<
b101 !
b101 *
b101 /
b101 0
b11 A
b10 %
b10 (
b10 -
#29000
b1011111 "
b1011111 &
b1011111 )
13
1=
b110 !
b110 *
b110 /
b110 0
b100 A
b11 %
b11 (
b11 -
#30000
16
04
03
02
b1110000 "
b1110000 &
b1110000 )
01
1:
0<
0=
0>
0?
b111 !
b111 *
b111 /
b111 0
b101 A
b100 %
b100 (
b100 -
#31000
14
13
12
b1111111 "
b1111111 &
b1111111 )
11
1<
1=
1>
1?
b1000 !
b1000 *
b1000 /
b1000 0
b110 A
b101 %
b101 (
b101 -
#32000
b1111011 "
b1111011 &
b1111011 )
03
0=
b1001 !
b1001 *
b1001 /
b1001 0
b111 A
b110 %
b110 (
b110 -
#33000
04
b1110111 "
b1110111 &
b1110111 )
13
0<
1=
b1010 !
b1010 *
b1010 /
b1010 0
b100 @
b0 A
b111 %
b111 (
b111 -
#34000
07
b110011 "
b110011 &
b110011 )
03
09
0=
b100 !
b100 *
b100 /
b100 0
b1 A
b0 %
b0 (
b0 -
b100 $
b100 '
b100 ,
#35000
17
06
b1011011 "
b1011011 &
b1011011 )
14
19
0:
1<
b101 !
b101 *
b101 /
b101 0
b10 A
b1 %
b1 (
b1 -
#36000
b1011111 "
b1011111 &
b1011111 )
13
1=
b110 !
b110 *
b110 /
b110 0
b11 A
b10 %
b10 (
b10 -
#37000
16
04
03
02
b1110000 "
b1110000 &
b1110000 )
01
1:
0<
0=
0>
0?
b111 !
b111 *
b111 /
b111 0
b100 A
b11 %
b11 (
b11 -
#38000
14
13
12
b1111111 "
b1111111 &
b1111111 )
11
1<
1=
1>
1?
b1000 !
b1000 *
b1000 /
b1000 0
b101 A
b100 %
b100 (
b100 -
#39000
b1111011 "
b1111011 &
b1111011 )
03
0=
b1001 !
b1001 *
b1001 /
b1001 0
b110 A
b101 %
b101 (
b101 -
#40000
04
b1110111 "
b1110111 &
b1110111 )
13
0<
1=
b1010 !
b1010 *
b1010 /
b1010 0
b111 A
b110 %
b110 (
b110 -
#41000
07
06
b11111 "
b11111 &
b11111 )
14
09
0:
1<
b1011 !
b1011 *
b1011 /
b1011 0
b101 @
b0 A
b111 %
b111 (
b111 -
#42000
17
b1011011 "
b1011011 &
b1011011 )
03
19
0=
b101 !
b101 *
b101 /
b101 0
b1 A
b0 %
b0 (
b0 -
b101 $
b101 '
b101 ,
#43000
b1011111 "
b1011111 &
b1011111 )
13
1=
b110 !
b110 *
b110 /
b110 0
b10 A
b1 %
b1 (
b1 -
#44000
16
04
03
02
b1110000 "
b1110000 &
b1110000 )
01
1:
0<
0=
0>
0?
b111 !
b111 *
b111 /
b111 0
b11 A
b10 %
b10 (
b10 -
#45000
14
13
12
b1111111 "
b1111111 &
b1111111 )
11
1<
1=
1>
1?
b1000 !
b1000 *
b1000 /
b1000 0
b100 A
b11 %
b11 (
b11 -
#46000
b1111011 "
b1111011 &
b1111011 )
03
0=
b1001 !
b1001 *
b1001 /
b1001 0
b101 A
b100 %
b100 (
b100 -
#47000
04
b1110111 "
b1110111 &
b1110111 )
13
0<
1=
b1010 !
b1010 *
b1010 /
b1010 0
b110 A
b101 %
b101 (
b101 -
#48000
07
06
b11111 "
b11111 &
b11111 )
14
09
0:
1<
b1011 !
b1011 *
b1011 /
b1011 0
b111 A
b110 %
b110 (
b110 -
#49000
17
05
b1001110 "
b1001110 &
b1001110 )
01
19
0;
0?
b1100 !
b1100 *
b1100 /
b1100 0
b110 @
b0 A
b111 %
b111 (
b111 -
#50000
15
b1011111 "
b1011111 &
b1011111 )
11
1;
1?
b110 !
b110 *
b110 /
b110 0
b1 A
b0 %
b0 (
b0 -
b110 $
b110 '
b110 ,
#51000
16
04
03
02
b1110000 "
b1110000 &
b1110000 )
01
1:
0<
0=
0>
0?
b111 !
b111 *
b111 /
b111 0
b10 A
b1 %
b1 (
b1 -
#52000
14
13
12
b1111111 "
b1111111 &
b1111111 )
11
1<
1=
1>
1?
b1000 !
b1000 *
b1000 /
b1000 0
b11 A
b10 %
b10 (
b10 -
#53000
b1111011 "
b1111011 &
b1111011 )
03
0=
b1001 !
b1001 *
b1001 /
b1001 0
b100 A
b11 %
b11 (
b11 -
#54000
04
b1110111 "
b1110111 &
b1110111 )
13
0<
1=
b1010 !
b1010 *
b1010 /
b1010 0
b101 A
b100 %
b100 (
b100 -
#55000
07
06
b11111 "
b11111 &
b11111 )
14
09
0:
1<
b1011 !
b1011 *
b1011 /
b1011 0
b110 A
b101 %
b101 (
b101 -
#56000
17
05
b1001110 "
b1001110 &
b1001110 )
01
19
0;
0?
b1100 !
b1100 *
b1100 /
b1100 0
b111 A
b110 %
b110 (
b110 -
#57000
07
16
15
02
b111101 "
b111101 &
b111101 )
11
09
1:
1;
0>
1?
b1101 !
b1101 *
b1101 /
b1101 0
b111 @
b0 A
b111 %
b111 (
b111 -
#58000
17
04
03
b1110000 "
b1110000 &
b1110000 )
01
19
0<
0=
0?
b111 !
b111 *
b111 /
b111 0
b1 A
b0 %
b0 (
b0 -
b111 $
b111 '
b111 ,
#59000
14
13
12
b1111111 "
b1111111 &
b1111111 )
11
1<
1=
1>
1?
b1000 !
b1000 *
b1000 /
b1000 0
b10 A
b1 %
b1 (
b1 -
#60000
b1111011 "
b1111011 &
b1111011 )
03
0=
b1001 !
b1001 *
b1001 /
b1001 0
b11 A
b10 %
b10 (
b10 -
#61000
04
b1110111 "
b1110111 &
b1110111 )
13
0<
1=
b1010 !
b1010 *
b1010 /
b1010 0
b100 A
b11 %
b11 (
b11 -
#62000
07
06
b11111 "
b11111 &
b11111 )
14
09
0:
1<
b1011 !
b1011 *
b1011 /
b1011 0
b101 A
b100 %
b100 (
b100 -
#63000
17
05
b1001110 "
b1001110 &
b1001110 )
01
19
0;
0?
b1100 !
b1100 *
b1100 /
b1100 0
b110 A
b101 %
b101 (
b101 -
#64000
07
16
15
02
b111101 "
b111101 &
b111101 )
11
09
1:
1;
0>
1?
b1101 !
b1101 *
b1101 /
b1101 0
b111 A
b110 %
b110 (
b110 -
#65000
17
06
05
b1001111 "
b1001111 &
b1001111 )
12
19
0:
0;
1>
b1110 !
b1110 *
b1110 /
b1110 0
b1000 @
b1000 A
b111 %
b111 (
b111 -
